odoo/addons/fieldservice_sale_stock/README.rst
odoo/addons/fieldservice_sale_stock/__init__.py
odoo/addons/fieldservice_sale_stock/__manifest__.py
odoo/addons/fieldservice_sale_stock/i18n/es.po
odoo/addons/fieldservice_sale_stock/i18n/es_AR.po
odoo/addons/fieldservice_sale_stock/i18n/es_CL.po
odoo/addons/fieldservice_sale_stock/i18n/fieldservice_sale_stock.pot
odoo/addons/fieldservice_sale_stock/i18n/it.po
odoo/addons/fieldservice_sale_stock/i18n/pt_BR.po
odoo/addons/fieldservice_sale_stock/models/__init__.py
odoo/addons/fieldservice_sale_stock/models/sale_order.py
odoo/addons/fieldservice_sale_stock/readme/CONFIGURE.rst
odoo/addons/fieldservice_sale_stock/readme/CONTRIBUTORS.rst
odoo/addons/fieldservice_sale_stock/readme/DESCRIPTION.rst
odoo/addons/fieldservice_sale_stock/readme/INSTALL.rst
odoo/addons/fieldservice_sale_stock/readme/ROADMAP.rst
odoo/addons/fieldservice_sale_stock/readme/USAGE.rst
odoo/addons/fieldservice_sale_stock/static/description/icon.png
odoo/addons/fieldservice_sale_stock/static/description/index.html
odoo/addons/fieldservice_sale_stock/tests/__init__.py
odoo/addons/fieldservice_sale_stock/tests/test_fsm_sale_order.py
odoo14_addon_fieldservice_sale_stock-14.0.1.0.1.dev11.dist-info/METADATA
odoo14_addon_fieldservice_sale_stock-14.0.1.0.1.dev11.dist-info/WHEEL
odoo14_addon_fieldservice_sale_stock-14.0.1.0.1.dev11.dist-info/top_level.txt
odoo14_addon_fieldservice_sale_stock-14.0.1.0.1.dev11.dist-info/RECORD
